{
  "af-south-1": {
    "AdvancedWaf200Mbps": "ami-0ab1270c760ba8fd9",
    "AdvancedWaf25Mbps": "ami-0a035a42ebcc1e05f",
    "Best10000Mbps": "ami-034e700c43367b7e0",
    "Best1000Mbps": "ami-034e96039221abbe4",
    "Best200Mbps": "ami-0532d318a6248f886",
    "Best25Mbps": "ami-0edcc9a182407b128",
    "Best5000Mbps": "ami-0afe538132925cd99",
    "Better10000Mbps": "ami-09d406bb487fc84b0",
    "Better1000Mbps": "ami-0a156386a1b3ebcf3",
    "Better200Mbps": "ami-049451efee27c6641",
    "Better25Mbps": "ami-0cf60e9fe9ef777ee",
    "Better5000Mbps": "ami-08be027a2cc68f760",
    "Good10000Mbps": "ami-0c068c5f6de909160",
    "Good1000Mbps": "ami-0d00bf680b9dfc858",
    "Good200Mbps": "ami-00e7bdd32514da815",
    "Good25Mbps": "ami-0b0a53f2b8c7c2c85",
    "Good5000Mbps": "ami-095dd0dc36e0456d6",
    "PerAppVeAwaf200Mbps": "ami-0569d1ce0d04b3e5c",
    "PerAppVeAwaf25Mbps": "ami-0a4adb0481bbf4fee"
  },
  "ap-east-1": {
    "AdvancedWaf200Mbps": "ami-071ac2ea31bf47ba3",
    "AdvancedWaf25Mbps": "ami-07ec5c55630533dd8",
    "Best10000Mbps": "ami-090f076e7faa488b1",
    "Best1000Mbps": "ami-08624ba08a40b8971",
    "Best200Mbps": "ami-001b7b542964d7ebc",
    "Best25Mbps": "ami-0e2736e98142c4734",
    "Best5000Mbps": "ami-063511561754ee438",
    "Better10000Mbps": "ami-098d491031ffd5752",
    "Better1000Mbps": "ami-0c545c249a057c940",
    "Better200Mbps": "ami-047210b42d2087523",
    "Better25Mbps": "ami-01f5b20d2b4b60676",
    "Better5000Mbps": "ami-06d8a39a5b0a2fc99",
    "Good10000Mbps": "ami-0d0f660b83537061d",
    "Good1000Mbps": "ami-083d2f042b271b449",
    "Good200Mbps": "ami-051a3f84369f904fc",
    "Good25Mbps": "ami-01ff3c391acccca60",
    "Good5000Mbps": "ami-02e31d8b2afaad25a",
    "PerAppVeAwaf200Mbps": "ami-0489dee06e7f0bc14",
    "PerAppVeAwaf25Mbps": "ami-0389a98c981824703"
  },
  "ap-northeast-1": {
    "AdvancedWaf200Mbps": "ami-00815ed7d678bbc90",
    "AdvancedWaf25Mbps": "ami-09cd58c2038cf0c57",
    "Best10000Mbps": "ami-01ae4d03acdac4b1c",
    "Best1000Mbps": "ami-0189c23e787361727",
    "Best200Mbps": "ami-02951f64aa51d4c20",
    "Best25Mbps": "ami-06e406e48e4ca5664",
    "Best5000Mbps": "ami-0f66258338771e048",
    "Better10000Mbps": "ami-09bd62fbcb7cbe9a5",
    "Better1000Mbps": "ami-01782b8ca0081cb59",
    "Better200Mbps": "ami-0bc005b205d943596",
    "Better25Mbps": "ami-0cfa29a36ec91223b",
    "Better5000Mbps": "ami-0ba14d1e223c1433c",
    "Good10000Mbps": "ami-0420d8bf695ad7072",
    "Good1000Mbps": "ami-0be8926ffb9a963da",
    "Good200Mbps": "ami-0b51562dd19960e28",
    "Good25Mbps": "ami-0ae7894d576ba290b",
    "Good5000Mbps": "ami-0271c89d95cb00b2a",
    "PerAppVeAwaf200Mbps": "ami-09a6198a9fe42cb56",
    "PerAppVeAwaf25Mbps": "ami-0f422b34d798b2b65"
  },
  "ap-northeast-2": {
    "AdvancedWaf200Mbps": "ami-08f9e8283cbf93e65",
    "AdvancedWaf25Mbps": "ami-03175e71da4071e3c",
    "Best10000Mbps": "ami-0a95e7af95c1075e6",
    "Best1000Mbps": "ami-0fce3f34b1b106b4f",
    "Best200Mbps": "ami-04f44f32ca4469b1d",
    "Best25Mbps": "ami-0677c2e7ab2f589ee",
    "Best5000Mbps": "ami-0e36f3ebb19bbae40",
    "Better10000Mbps": "ami-0adc2044cb6fbc1ec",
    "Better1000Mbps": "ami-09b72cc6ae981dd2b",
    "Better200Mbps": "ami-0979b91dbdbb92f4f",
    "Better25Mbps": "ami-027dc59ef6ef55d6f",
    "Better5000Mbps": "ami-099481eed76ed3de3",
    "Good10000Mbps": "ami-0efd4b70819beb8c6",
    "Good1000Mbps": "ami-090034bbfca534bb2",
    "Good200Mbps": "ami-0f62b50d0834d7cb5",
    "Good25Mbps": "ami-0a300c61059d863f1",
    "Good5000Mbps": "ami-00b9efc19663eab57",
    "PerAppVeAwaf200Mbps": "ami-00e5e4ef61ed1c089",
    "PerAppVeAwaf25Mbps": "ami-0f86df54bcfd1532d"
  },
  "ap-northeast-3": {
    "AdvancedWaf200Mbps": "ami-05dc63e078de15433",
    "AdvancedWaf25Mbps": "ami-08cbd3824afd498d4",
    "Best10000Mbps": "ami-09ee185c5114081dd",
    "Best1000Mbps": "ami-0c6d64f3dfe7d5258",
    "Best200Mbps": "ami-0486a3de02ec4beb3",
    "Best25Mbps": "ami-0528935e3172da52f",
    "Best5000Mbps": "ami-0b58d32519cd71a88",
    "Better10000Mbps": "ami-01cc03715f1548cab",
    "Better1000Mbps": "ami-036cf5834bbcb5fa2",
    "Better200Mbps": "ami-0216a98426e16636a",
    "Better25Mbps": "ami-0bc800bda590353ef",
    "Better5000Mbps": "ami-035ce0a4d1a397ad7",
    "Good10000Mbps": "ami-0c05c168d52ba8961",
    "Good1000Mbps": "ami-0140570f19ac388ae",
    "Good200Mbps": "ami-0e253f3f42a27d489",
    "Good25Mbps": "ami-0b6ff2a461980a8bc",
    "Good5000Mbps": "ami-084a7617b9491e4e8",
    "PerAppVeAwaf200Mbps": "ami-0d4aac2b6bb246a2e",
    "PerAppVeAwaf25Mbps": "ami-06573daf169ed0146"
  },
  "ap-south-1": {
    "AdvancedWaf200Mbps": "ami-0b74bdb549336c0c3",
    "AdvancedWaf25Mbps": "ami-06618c239042e56e7",
    "Best10000Mbps": "ami-057852c1b43196f70",
    "Best1000Mbps": "ami-000a93f9b406b1f2c",
    "Best200Mbps": "ami-03432e6745d7fe096",
    "Best25Mbps": "ami-032b29c51b0bd1410",
    "Best5000Mbps": "ami-0da3464b2ded1716c",
    "Better10000Mbps": "ami-0094d29e9aa330242",
    "Better1000Mbps": "ami-003a759884138f75e",
    "Better200Mbps": "ami-0d4f4c01268ab9b4d",
    "Better25Mbps": "ami-0806353a5b440ecbf",
    "Better5000Mbps": "ami-09824a542f6457164",
    "Good10000Mbps": "ami-0e94f92bf5e0fabae",
    "Good1000Mbps": "ami-0e3cdf4e1ad81f3ef",
    "Good200Mbps": "ami-0afb48b00ea280285",
    "Good25Mbps": "ami-043f2fb2109d299d4",
    "Good5000Mbps": "ami-06b629f7923e41dd5",
    "PerAppVeAwaf200Mbps": "ami-054937a44f655871a",
    "PerAppVeAwaf25Mbps": "ami-0fd99bb783cd3a706"
  },
  "ap-southeast-1": {
    "AdvancedWaf200Mbps": "ami-0b08b2fe87bd67ac5",
    "AdvancedWaf25Mbps": "ami-04d2234331485bd67",
    "Best10000Mbps": "ami-0d57f1679f3971b87",
    "Best1000Mbps": "ami-06109b89cef4c9b7f",
    "Best200Mbps": "ami-0648c671af9221dc0",
    "Best25Mbps": "ami-0e625015e71175852",
    "Best5000Mbps": "ami-08f8fb78b6ddc5d7a",
    "Better10000Mbps": "ami-0dcf5b1001db4a04b",
    "Better1000Mbps": "ami-0ac2ab5d2977c5d09",
    "Better200Mbps": "ami-0bf95f748e2c221c2",
    "Better25Mbps": "ami-026e8e1634c1cf517",
    "Better5000Mbps": "ami-021d6a535cf567917",
    "Good10000Mbps": "ami-018099ea1f738949d",
    "Good1000Mbps": "ami-0b43add7ffa9a3272",
    "Good200Mbps": "ami-030c7f0a0ab398a5b",
    "Good25Mbps": "ami-066e0eb1f90862005",
    "Good5000Mbps": "ami-0eadc7ab73019bbf3",
    "PerAppVeAwaf200Mbps": "ami-017391908ec271ae1",
    "PerAppVeAwaf25Mbps": "ami-0c12c44a6de2b6116"
  },
  "ap-southeast-2": {
    "AdvancedWaf200Mbps": "ami-06ec3fa430680dd09",
    "AdvancedWaf25Mbps": "ami-0d250cc0aeb29126c",
    "Best10000Mbps": "ami-01351c04a5aa7b28b",
    "Best1000Mbps": "ami-093c7a082d70d1f37",
    "Best200Mbps": "ami-0ffdbd14a8432743e",
    "Best25Mbps": "ami-007393c4b35d87832",
    "Best5000Mbps": "ami-00f922c73959ef2d1",
    "Better10000Mbps": "ami-05f83bc424358f9e7",
    "Better1000Mbps": "ami-005805b827dbd7356",
    "Better200Mbps": "ami-0d04693270f2b13d9",
    "Better25Mbps": "ami-0187ce4e6c954de80",
    "Better5000Mbps": "ami-0738dfcb07f7f8899",
    "Good10000Mbps": "ami-0f3422432db14522e",
    "Good1000Mbps": "ami-090abff768267c9b2",
    "Good200Mbps": "ami-0a7554016040bde64",
    "Good25Mbps": "ami-058fda34b129f708a",
    "Good5000Mbps": "ami-08b753659d200a2a9",
    "PerAppVeAwaf200Mbps": "ami-0aa221b6b775e5abd",
    "PerAppVeAwaf25Mbps": "ami-0c8ab14f5f08f7a51"
  },
  "ca-central-1": {
    "AdvancedWaf200Mbps": "ami-0e9e236202ecfd461",
    "AdvancedWaf25Mbps": "ami-000f51cf3b8ce4e7d",
    "Best10000Mbps": "ami-0140450ae034ef1b1",
    "Best1000Mbps": "ami-0562a210d53f7a34a",
    "Best200Mbps": "ami-0de08975a5b31eca1",
    "Best25Mbps": "ami-09506a2203bb39b55",
    "Best5000Mbps": "ami-019ee526dd785680e",
    "Better10000Mbps": "ami-0532bcbed54793ce6",
    "Better1000Mbps": "ami-078c2088199bbec27",
    "Better200Mbps": "ami-07fedc840a283dfc2",
    "Better25Mbps": "ami-0881836e318b9c5c2",
    "Better5000Mbps": "ami-0d4b15fa5a50dacc4",
    "Good10000Mbps": "ami-05913ea21fc170a2b",
    "Good1000Mbps": "ami-0b6a37db60bfa8c20",
    "Good200Mbps": "ami-00331bfb02269ab6a",
    "Good25Mbps": "ami-00005259424d8fb10",
    "Good5000Mbps": "ami-0d2cdf863f4fb95b1",
    "PerAppVeAwaf200Mbps": "ami-07c43bacb0e8eb8c0",
    "PerAppVeAwaf25Mbps": "ami-080c5f21871a089ed"
  },
  "eu-central-1": {
    "AdvancedWaf200Mbps": "ami-0820fec9e1d274ced",
    "AdvancedWaf25Mbps": "ami-02eb0f0533350ebb3",
    "Best10000Mbps": "ami-03c517467afd123de",
    "Best1000Mbps": "ami-0fc92ad829896e650",
    "Best200Mbps": "ami-0c24005e6ad0945d0",
    "Best25Mbps": "ami-009a32178c5cdbedf",
    "Best5000Mbps": "ami-01bc9d704bc3cc571",
    "Better10000Mbps": "ami-0e184cc294f464fc4",
    "Better1000Mbps": "ami-0d45529e7fcff90e0",
    "Better200Mbps": "ami-0ec24b92bb321087c",
    "Better25Mbps": "ami-0a25c549936cbdec2",
    "Better5000Mbps": "ami-0f559e4b384136bf8",
    "Good10000Mbps": "ami-0a317be0bf962f712",
    "Good1000Mbps": "ami-009214492fffae630",
    "Good200Mbps": "ami-025cd45fb6eedf9b3",
    "Good25Mbps": "ami-0a133364b7c7078f1",
    "Good5000Mbps": "ami-02e186c9553a9498a",
    "PerAppVeAwaf200Mbps": "ami-0b7033a7c9441cca6",
    "PerAppVeAwaf25Mbps": "ami-037ebe367b45326af"
  },
  "eu-north-1": {
    "AdvancedWaf200Mbps": "ami-0dbbda7af917b9a4a",
    "AdvancedWaf25Mbps": "ami-0533d84ff6939ae6c",
    "Best10000Mbps": "ami-0009c7ab725b52826",
    "Best1000Mbps": "ami-065a177f187992278",
    "Best200Mbps": "ami-03a86f249b02c6445",
    "Best25Mbps": "ami-08b553a7a3332a712",
    "Best5000Mbps": "ami-09df5b99f03c95809",
    "Better10000Mbps": "ami-0f5267b295eec5f9c",
    "Better1000Mbps": "ami-0f733acdc23890102",
    "Better200Mbps": "ami-0db0a2b2d102e0abb",
    "Better25Mbps": "ami-0e4a2c1539a55d2b7",
    "Better5000Mbps": "ami-0faa6e8fe7eee6070",
    "Good10000Mbps": "ami-04cd2a383a18f78d7",
    "Good1000Mbps": "ami-06fee3ac1a2340ea6",
    "Good200Mbps": "ami-01ce6742eae52da38",
    "Good25Mbps": "ami-0fd792fa0bb71f561",
    "Good5000Mbps": "ami-07ed83854950aae78",
    "PerAppVeAwaf200Mbps": "ami-0f65111826c779d6c",
    "PerAppVeAwaf25Mbps": "ami-094757e9b43307312"
  },
  "eu-south-1": {
    "AdvancedWaf200Mbps": "ami-0959a819062b0c5b3",
    "AdvancedWaf25Mbps": "ami-0a57a6523caa84bea",
    "Best10000Mbps": "ami-0352378b7762efdf9",
    "Best1000Mbps": "ami-0397c835ebf3124e8",
    "Best200Mbps": "ami-076b06593087881f9",
    "Best25Mbps": "ami-06ed831e47e11aff6",
    "Best5000Mbps": "ami-02130ca17fe0f3cfe",
    "Better10000Mbps": "ami-078231fb7a6f910aa",
    "Better1000Mbps": "ami-04015a8e18e9b95cc",
    "Better200Mbps": "ami-0860720b62b37a7c9",
    "Better25Mbps": "ami-00c509b4716cf1c52",
    "Better5000Mbps": "ami-0dc085cf855fab15e",
    "Good10000Mbps": "ami-0e04e8ef8e3a0132a",
    "Good1000Mbps": "ami-0046e698a4c12a300",
    "Good200Mbps": "ami-0d96e410b2f1b0b68",
    "Good25Mbps": "ami-0852990310e8d21a8",
    "Good5000Mbps": "ami-05d0717816970e4bd",
    "PerAppVeAwaf200Mbps": "ami-0a111b3b800573da2",
    "PerAppVeAwaf25Mbps": "ami-0c3ddb8ed4402a953"
  },
  "eu-west-1": {
    "AdvancedWaf200Mbps": "ami-0aebde6c9b356e4db",
    "AdvancedWaf25Mbps": "ami-08f17f8779f16d922",
    "Best10000Mbps": "ami-08320763bc8a9eab8",
    "Best1000Mbps": "ami-001a3cb1af51b245c",
    "Best200Mbps": "ami-0ee0cabcfa15c7c27",
    "Best25Mbps": "ami-0e41009ca5c4bff4c",
    "Best5000Mbps": "ami-05d0e93bc034a3824",
    "Better10000Mbps": "ami-037f49d858f16be4b",
    "Better1000Mbps": "ami-07072275d216cbc23",
    "Better200Mbps": "ami-0234005a4f04fd15c",
    "Better25Mbps": "ami-0fb8789dda53a2aff",
    "Better5000Mbps": "ami-0e0b55afda1be4490",
    "Good10000Mbps": "ami-0fd0b3696b6c719f8",
    "Good1000Mbps": "ami-07e437dc757d35add",
    "Good200Mbps": "ami-0897a9b1343076216",
    "Good25Mbps": "ami-07dd702408df1f359",
    "Good5000Mbps": "ami-0b7f99c98ae83c98e",
    "PerAppVeAwaf200Mbps": "ami-0c8e1215b8421b090",
    "PerAppVeAwaf25Mbps": "ami-039acbc7e3e9d10c6"
  },
  "eu-west-2": {
    "AdvancedWaf200Mbps": "ami-00f1c5dba7b90a63b",
    "AdvancedWaf25Mbps": "ami-0d30886c12a3bd941",
    "Best10000Mbps": "ami-0b7246459c64b0ccb",
    "Best1000Mbps": "ami-08fb304ef0aea357a",
    "Best200Mbps": "ami-0a652c87361fa80e8",
    "Best25Mbps": "ami-05d68549f9e576535",
    "Best5000Mbps": "ami-0736c6ccc7babc3ab",
    "Better10000Mbps": "ami-0c39a7f1d3b925c1e",
    "Better1000Mbps": "ami-0979e2dda86ef2a61",
    "Better200Mbps": "ami-0cf3f6fdba5b4310e",
    "Better25Mbps": "ami-0437addd3fdf3693d",
    "Better5000Mbps": "ami-07e8468b5044d22e8",
    "Good10000Mbps": "ami-0bacf64c7247b4f7d",
    "Good1000Mbps": "ami-0d3f7617bac85bc13",
    "Good200Mbps": "ami-001d7aa043da7ebb5",
    "Good25Mbps": "ami-0cce9f022f278212e",
    "Good5000Mbps": "ami-002ea70ad1f309466",
    "PerAppVeAwaf200Mbps": "ami-0dc1b47f97c60d262",
    "PerAppVeAwaf25Mbps": "ami-0f4e4073275bc61e5"
  },
  "eu-west-3": {
    "AdvancedWaf200Mbps": "ami-0a26429abdc4e095b",
    "AdvancedWaf25Mbps": "ami-0bb129f9b113170aa",
    "Best10000Mbps": "ami-09c1ad8dd79173383",
    "Best1000Mbps": "ami-0c946229b8c91e8aa",
    "Best200Mbps": "ami-017425096090ee7fa",
    "Best25Mbps": "ami-073597f4624856a56",
    "Best5000Mbps": "ami-025366aaf2f414058",
    "Better10000Mbps": "ami-097adb90e63abbeb7",
    "Better1000Mbps": "ami-07800029ee30cef48",
    "Better200Mbps": "ami-050e4e6b0d35e8456",
    "Better25Mbps": "ami-0f8aa1b786e3a9ea4",
    "Better5000Mbps": "ami-03b2f5e2e4e66c4d6",
    "Good10000Mbps": "ami-0b52aba4bf59dddaa",
    "Good1000Mbps": "ami-024653f31a5a7079b",
    "Good200Mbps": "ami-039cb50d452ebb371",
    "Good25Mbps": "ami-08db2d3dba2cb2ba3",
    "Good5000Mbps": "ami-0d6a369a256a374f3",
    "PerAppVeAwaf200Mbps": "ami-01ef433261be752e6",
    "PerAppVeAwaf25Mbps": "ami-03a23593e149bc0e9"
  },
  "me-south-1": {
    "AdvancedWaf200Mbps": "ami-0ee624903cfe14054",
    "AdvancedWaf25Mbps": "ami-0d2e1857c69904ad1",
    "Best10000Mbps": "ami-02a3a5f6ffdcb802f",
    "Best1000Mbps": "ami-0b1ababa38256658f",
    "Best200Mbps": "ami-08ca07d21d116d5c6",
    "Best25Mbps": "ami-0480695bb3161ca26",
    "Best5000Mbps": "ami-02c664a973276f33f",
    "Better10000Mbps": "ami-09042e2229bbbd43d",
    "Better1000Mbps": "ami-071a147f1409ff8bb",
    "Better200Mbps": "ami-0a031b7c0d38f0934",
    "Better25Mbps": "ami-0c81f91a966bbbceb",
    "Better5000Mbps": "ami-05479148055291382",
    "Good10000Mbps": "ami-0b1c699576908b7f2",
    "Good1000Mbps": "ami-0cfc0057e0170def8",
    "Good200Mbps": "ami-08ee74b80fd438c1a",
    "Good25Mbps": "ami-053a30f4195345950",
    "Good5000Mbps": "ami-0a549a26766b72af4",
    "PerAppVeAwaf200Mbps": "ami-01a5fbe09cba487a1",
    "PerAppVeAwaf25Mbps": "ami-0fe010571f78c6bf5"
  },
  "sa-east-1": {
    "AdvancedWaf200Mbps": "ami-007ade6ce48db6673",
    "AdvancedWaf25Mbps": "ami-0e85c619390339941",
    "Best10000Mbps": "ami-05cdca96364f2481c",
    "Best1000Mbps": "ami-017336ea3461d6674",
    "Best200Mbps": "ami-0f2b4687d938e00b9",
    "Best25Mbps": "ami-0a433f050db23dbc3",
    "Best5000Mbps": "ami-02396804c8b07c14a",
    "Better10000Mbps": "ami-032e8a9100b0e63c2",
    "Better1000Mbps": "ami-037612372a1d4bcfa",
    "Better200Mbps": "ami-0a0b2357fe11a692f",
    "Better25Mbps": "ami-0d4b22eaa2446f2aa",
    "Better5000Mbps": "ami-00d4a60ecc741ccbd",
    "Good10000Mbps": "ami-05c5011b135e8264e",
    "Good1000Mbps": "ami-00209af61f1744eb8",
    "Good200Mbps": "ami-09c8441849b9d3ecb",
    "Good25Mbps": "ami-017d92d4670b25de6",
    "Good5000Mbps": "ami-0cede0641a62246fb",
    "PerAppVeAwaf200Mbps": "ami-09534e5f902b88f39",
    "PerAppVeAwaf25Mbps": "ami-01a7c251c7e26f345"
  },
  "us-east-1": {
    "Better5000Mbps": "ami-00ce5bcbe84175acc"
  },
  "us-east-2": {
    "AdvancedWaf200Mbps": "ami-0416d402a5aaf6eec",
    "AdvancedWaf25Mbps": "ami-0604d8b6cb46b0178",
    "Best10000Mbps": "ami-0a22ef3afab16c2ab",
    "Best1000Mbps": "ami-0585e99d8c1eabe7f",
    "Best200Mbps": "ami-018cfba3201780350",
    "Best25Mbps": "ami-0bfb7d05d3db19eb3",
    "Best5000Mbps": "ami-0d0961a9a32e5572c",
    "Better10000Mbps": "ami-0a6d349a5203ad141",
    "Better1000Mbps": "ami-01389c8572f983603",
    "Better200Mbps": "ami-0976e83c778153032",
    "Better25Mbps": "ami-0cb77fa08970669cb",
    "Better5000Mbps": "ami-0b087755c9cc36f8e",
    "Good10000Mbps": "ami-0131df4631592f167",
    "Good1000Mbps": "ami-027a4515205670d2c",
    "Good200Mbps": "ami-0bc6eca8ab432a285",
    "Good25Mbps": "ami-00ec6714af7396d3a",
    "Good5000Mbps": "ami-0c061f2c96be28505",
    "PerAppVeAwaf200Mbps": "ami-0b2659cfcfb325397",
    "PerAppVeAwaf25Mbps": "ami-0eba4fb2f86a6bb48"
  },
  "us-gov-east-1": {
    "AdvancedWaf200Mbps": "ami-008ac272b0f10d7f4",
    "AdvancedWaf25Mbps": "ami-0d9fd41cdb67d4d50",
    "Best10000Mbps": "ami-0fa2fbd0d29bc8e20",
    "Best1000Mbps": "ami-0ee31792cb3d26b1b",
    "Best200Mbps": "ami-0859171c390773b52",
    "Best25Mbps": "ami-0b7c418f28703ae74",
    "Best5000Mbps": "ami-0f3facc0d3d86181c",
    "Better10000Mbps": "ami-0e39cb52148d0b472",
    "Better1000Mbps": "ami-07c0598356f4e212a",
    "Better200Mbps": "ami-0f0329a84e95722d5",
    "Better25Mbps": "ami-020e4fdb09285cfdf",
    "Better5000Mbps": "ami-0c8ea090893d53dc3",
    "Good10000Mbps": "ami-07ac4de85820c9791",
    "Good1000Mbps": "ami-0d9c2e8b883c3d308",
    "Good200Mbps": "ami-0d6db7d33467d27db",
    "Good25Mbps": "ami-07ea999a02ca1d1a0",
    "Good5000Mbps": "ami-03446e8709afd323d",
    "PerAppVeAwaf200Mbps": "ami-0b123c60ff72c4230",
    "PerAppVeAwaf25Mbps": "ami-0a0ff241ba5378d33"
  },
  "us-gov-west-1": {
    "AdvancedWaf200Mbps": "ami-059875562e889e93b",
    "AdvancedWaf25Mbps": "ami-063861f0b43059b4b",
    "Best10000Mbps": "ami-00f329bd5827bb0e4",
    "Best1000Mbps": "ami-0b49b294ba532f52e",
    "Best200Mbps": "ami-097244ed97264ca10",
    "Best25Mbps": "ami-04dcddc3998e84c97",
    "Best5000Mbps": "ami-0ac6218d5eb0e2896",
    "Better10000Mbps": "ami-0eaaca62687adb34f",
    "Better1000Mbps": "ami-078e0b2a069c99c48",
    "Better200Mbps": "ami-0b1d58b1b6938b34d",
    "Better25Mbps": "ami-0ae945729c77f7c4b",
    "Better5000Mbps": "ami-08eacc613e715c17b",
    "Good10000Mbps": "ami-024b4a479425f6f73",
    "Good1000Mbps": "ami-0a505d0ce3b67ae66",
    "Good200Mbps": "ami-094e1b12b3d4070f5",
    "Good25Mbps": "ami-08af7fcde0426ce8f",
    "Good5000Mbps": "ami-0ceb42cb8617da7fc",
    "PerAppVeAwaf200Mbps": "ami-081f4241bc8bde4be",
    "PerAppVeAwaf25Mbps": "ami-01ee6c8c07d8bfeea"
  },
  "us-west-1": {
    "AdvancedWaf200Mbps": "ami-0a6fb575313e3f03b",
    "AdvancedWaf25Mbps": "ami-0a2a8003d33ed37bd",
    "Best10000Mbps": "ami-0cfe287c2075eaa2a",
    "Best1000Mbps": "ami-035918f48c772091b",
    "Best200Mbps": "ami-0ae589d7ccb6acaa8",
    "Best25Mbps": "ami-027d212e33cf562aa",
    "Best5000Mbps": "ami-04481ceca81b06a4c",
    "Better10000Mbps": "ami-063f31f447cfb8815",
    "Better1000Mbps": "ami-0db5f9025b17b8acf",
    "Better200Mbps": "ami-0b2786ae45b8d92b3",
    "Better25Mbps": "ami-00a268d712275339c",
    "Better5000Mbps": "ami-014ed143532b2ff32",
    "Good10000Mbps": "ami-0b3a0f4e6483f65af",
    "Good1000Mbps": "ami-0ba81657511716e31",
    "Good200Mbps": "ami-06d5db4b12df14858",
    "Good25Mbps": "ami-0a9e57eefdf7f89e1",
    "Good5000Mbps": "ami-0a7b0d0a43ba00bd8",
    "PerAppVeAwaf200Mbps": "ami-0dd64c35026c8accc",
    "PerAppVeAwaf25Mbps": "ami-0b51a909b58b66c39"
  },
  "us-west-2": {
    "AdvancedWaf200Mbps": "ami-0c34ea19583cf3928",
    "AdvancedWaf25Mbps": "ami-08fa954c5054c3afe",
    "Best10000Mbps": "ami-06f1841a3e5cb1132",
    "Best1000Mbps": "ami-095a63466516b04d6",
    "Best200Mbps": "ami-0851f29b41e65ee42",
    "Best25Mbps": "ami-0e12eace3ddf6b54c",
    "Best5000Mbps": "ami-004725e12f6bf8047",
    "Better10000Mbps": "ami-0fec504e7fc094874",
    "Better1000Mbps": "ami-00a1b77d715082336",
    "Better200Mbps": "ami-0e821c4248cbf9b1a",
    "Better25Mbps": "ami-0fc0507ea44edd65a",
    "Better5000Mbps": "ami-0946fe6adf8462946",
    "Good10000Mbps": "ami-01215d524f3aba5b9",
    "Good1000Mbps": "ami-0e32257f0c24821fa",
    "Good200Mbps": "ami-0c4decb41536bee58",
    "Good25Mbps": "ami-075ee7e16b68fa088",
    "Good5000Mbps": "ami-02d170b5039e5b877",
    "PerAppVeAwaf200Mbps": "ami-0d467bcb14a7d7337",
    "PerAppVeAwaf25Mbps": "ami-0955b0de4a0767e65"
  }
}