{
  "ap-east-1": {
    "AdvancedWaf1000Mbps": "ami-02dc6e2b760434f31",
    "AdvancedWaf16vCPU": "ami-09ac2e879ad6c5480",
    "AdvancedWaf200Mbps": "ami-0869b9c54ee135dce",
    "AdvancedWaf25Mbps": "ami-0e2bd8d51526ef796",
    "AdvancedWaf8vCPU": "ami-0713eb660565a72f2",
    "Best10000Mbps": "ami-0b091677c62d450cf",
    "Best1000Mbps": "ami-067a16bf06cc6a79d",
    "Best200Mbps": "ami-0d8d5ad6cc37285b6",
    "Best25Mbps": "ami-07c2a198f36b4fd22",
    "Best5000Mbps": "ami-0346ccabb71cd17be",
    "Better10000Mbps": "ami-05fb753d6d2287835",
    "Better1000Mbps": "ami-0f81ea6f30b4c7bdc",
    "Better200Mbps": "ami-0cd00f6e441efdeae",
    "Better25Mbps": "ami-0e9a1ec397afedf4f",
    "Better5000Mbps": "ami-01f2fdaf35ee7dde3",
    "Good10000Mbps": "ami-0e025231b2a487f75",
    "Good1000Mbps": "ami-0b2fb5de6ec91d2d5",
    "Good16vCPU": "ami-047eb20682339c12d",
    "Good200Mbps": "ami-03d1ce36996415e0b",
    "Good25Mbps": "ami-0f80693a687a25b9a",
    "Good5000Mbps": "ami-078c8e33731e2c275",
    "PerAppVeAwaf200Mbps": "ami-08d7a5675e88db49c",
    "PerAppVeAwaf25Mbps": "ami-048c152285c9f0ab3",
    "PerAppVeLtm200Mbps": "ami-0877591673f15c2e0",
    "PerAppVeLtm25Mbps": "ami-0df7fec5fd8deb004"
  },
  "ap-northeast-1": {
    "AdvancedWaf1000Mbps": "ami-03d8d1e6c9ef2eb1c",
    "AdvancedWaf16vCPU": "ami-0bdece97ca62994fb",
    "AdvancedWaf200Mbps": "ami-04b6aac7b22c8fc00",
    "AdvancedWaf25Mbps": "ami-0da59025e05b4db4e",
    "AdvancedWaf8vCPU": "ami-04e904f3a1fc125c0",
    "Best10000Mbps": "ami-038a5fd331629c5cb",
    "Best1000Mbps": "ami-07a4a27e1e142ffe2",
    "Best200Mbps": "ami-0fa4c8b5f2d6e27c2",
    "Best25Mbps": "ami-02b80e22bbe6bce12",
    "Best5000Mbps": "ami-0eae402b123efe5fc",
    "Better10000Mbps": "ami-0178310b33894097b",
    "Better1000Mbps": "ami-0124cbcfdb5e96b8a",
    "Better200Mbps": "ami-0f0a168b158254840",
    "Better25Mbps": "ami-03cb9a1d687aa3bfa",
    "Better5000Mbps": "ami-007516c4c64082464",
    "Good10000Mbps": "ami-0728932144254d6f8",
    "Good1000Mbps": "ami-0f1d895a997153c26",
    "Good16vCPU": "ami-0215cb9a1a3f4ebc8",
    "Good200Mbps": "ami-0154c9c5cb74d5474",
    "Good25Mbps": "ami-013ada262ba788ac3",
    "Good5000Mbps": "ami-0aa32f18e6471d3b0",
    "PerAppVeAwaf200Mbps": "ami-0a2dd8ea39030c3b6",
    "PerAppVeAwaf25Mbps": "ami-05f8a1722edc0527c",
    "PerAppVeLtm200Mbps": "ami-0eaa741154295180f",
    "PerAppVeLtm25Mbps": "ami-075232af7e1bdaa04"
  },
  "ap-northeast-2": {
    "AdvancedWaf1000Mbps": "ami-0090516e3c2b1efd3",
    "AdvancedWaf16vCPU": "ami-0718aec0c00ca5040",
    "AdvancedWaf200Mbps": "ami-042980b4306bd0117",
    "AdvancedWaf25Mbps": "ami-0f7bea77c64490a71",
    "AdvancedWaf8vCPU": "ami-0f6ece262c334f7ee",
    "Best10000Mbps": "ami-003fe113b6b2a253b",
    "Best1000Mbps": "ami-0df16b9dca2530df1",
    "Best200Mbps": "ami-0bebd48c3f1140fc1",
    "Best25Mbps": "ami-0d7dee253a2a8df59",
    "Best5000Mbps": "ami-014407fa019be4c74",
    "Better10000Mbps": "ami-0e60edf2681596d67",
    "Better1000Mbps": "ami-016ab5bc3ce41caf4",
    "Better200Mbps": "ami-03e49e8a421a8c71a",
    "Better25Mbps": "ami-0a60a39cec1239bae",
    "Better5000Mbps": "ami-04b128d622edd6af6",
    "Good10000Mbps": "ami-0386b2cdffc4d5862",
    "Good1000Mbps": "ami-0994d84b14085ddbe",
    "Good16vCPU": "ami-0aa00f1a003df284b",
    "Good200Mbps": "ami-0bd0ee1c958aef791",
    "Good25Mbps": "ami-06c4064fb858dd72b",
    "Good5000Mbps": "ami-09c929a793fb39e8d",
    "PerAppVeAwaf200Mbps": "ami-03e4a387c189776a7",
    "PerAppVeAwaf25Mbps": "ami-0df7f86f7227c4855",
    "PerAppVeLtm200Mbps": "ami-0f2dd94753bab3fe2",
    "PerAppVeLtm25Mbps": "ami-00c19400828469c51"
  },
  "ap-south-1": {
    "AdvancedWaf1000Mbps": "ami-0ded839acfc28c63c",
    "AdvancedWaf16vCPU": "ami-0202fac5920cab048",
    "AdvancedWaf200Mbps": "ami-0dd9e4623d1895f8f",
    "AdvancedWaf25Mbps": "ami-08de2d678def897dd",
    "AdvancedWaf8vCPU": "ami-0e92effd8ebdd984e",
    "Best10000Mbps": "ami-0fe60d86a019d4c78",
    "Best1000Mbps": "ami-0617e0ba92bad724e",
    "Best200Mbps": "ami-080aae837b67cb4f8",
    "Best25Mbps": "ami-00eee118fbac3b47a",
    "Best5000Mbps": "ami-0c7638286a4d40714",
    "Better10000Mbps": "ami-0280efa504ed1c626",
    "Better1000Mbps": "ami-0430d4560acb7a046",
    "Better200Mbps": "ami-0d1169e810e7a94a8",
    "Better25Mbps": "ami-060fbdef030580a3d",
    "Better5000Mbps": "ami-088766d89df2319d5",
    "Good10000Mbps": "ami-0c02c0a3c3157fba8",
    "Good1000Mbps": "ami-055d092b185f130a6",
    "Good16vCPU": "ami-05f10d2a6b8f95dc3",
    "Good200Mbps": "ami-07bb8836101ae164f",
    "Good25Mbps": "ami-0946368894f71a832",
    "Good5000Mbps": "ami-0910a3222a106e1e2",
    "PerAppVeAwaf200Mbps": "ami-0a0d95daeb96d13fe",
    "PerAppVeAwaf25Mbps": "ami-057c992bf45997066",
    "PerAppVeLtm200Mbps": "ami-0d8da3eb1d83f6ff1",
    "PerAppVeLtm25Mbps": "ami-0463ced887c3d3477"
  },
  "ap-southeast-1": {
    "AdvancedWaf1000Mbps": "ami-03604d85ecf2ad0e6",
    "AdvancedWaf16vCPU": "ami-0ec3c8b0c78244656",
    "AdvancedWaf200Mbps": "ami-0dd32216806719e1f",
    "AdvancedWaf25Mbps": "ami-013ae7b8e3b11572d",
    "AdvancedWaf8vCPU": "ami-054b46b6742f77e65",
    "Best10000Mbps": "ami-03994012b99d2ed38",
    "Best1000Mbps": "ami-086ec12ca612d42c4",
    "Best200Mbps": "ami-052453fc5f364df74",
    "Best25Mbps": "ami-0cf0d7140075eb210",
    "Best5000Mbps": "ami-0ba65e2d829366b75",
    "Better10000Mbps": "ami-0d103d1a13eb1ab76",
    "Better1000Mbps": "ami-05c16fad37e17c5cc",
    "Better200Mbps": "ami-024c73ac42d5ee577",
    "Better25Mbps": "ami-0d543045bf82fe237",
    "Better5000Mbps": "ami-0872c30bb52acc6cd",
    "Good10000Mbps": "ami-0c3f6a26d39275129",
    "Good1000Mbps": "ami-0a64f0b2a80abce25",
    "Good16vCPU": "ami-0b42bf4cec5fe40df",
    "Good200Mbps": "ami-071ab18f4e391ffff",
    "Good25Mbps": "ami-001a7a63432aec09a",
    "Good5000Mbps": "ami-039f110be38b6e9d9",
    "PerAppVeAwaf200Mbps": "ami-020fa4ed293042a8e",
    "PerAppVeAwaf25Mbps": "ami-0b23b6b3ac2bdf675",
    "PerAppVeLtm200Mbps": "ami-06d007537b048fe57",
    "PerAppVeLtm25Mbps": "ami-01fd64d04d40e5976"
  },
  "ap-southeast-2": {
    "AdvancedWaf1000Mbps": "ami-0ed5cc034b22ea84a",
    "AdvancedWaf16vCPU": "ami-0df72566c5ff418b4",
    "AdvancedWaf200Mbps": "ami-0e771ddf000ee1355",
    "AdvancedWaf25Mbps": "ami-07517880d2dc97f6f",
    "AdvancedWaf8vCPU": "ami-0044cbb4e1d582903",
    "Best10000Mbps": "ami-0a8881f642d9bbcf5",
    "Best1000Mbps": "ami-071b7ab13c281a587",
    "Best200Mbps": "ami-03d9ad8ff53136d58",
    "Best25Mbps": "ami-09e5ab62880304d00",
    "Best5000Mbps": "ami-0c5a552187d05344c",
    "Better10000Mbps": "ami-0c875f2c96f5b4022",
    "Better1000Mbps": "ami-061389ec60e4bbb83",
    "Better200Mbps": "ami-04fb591d85e32c066",
    "Better25Mbps": "ami-01ec1435ebf8d1c8c",
    "Better5000Mbps": "ami-0ca5a74d4fe561c6f",
    "Good10000Mbps": "ami-0123302557a39cbbd",
    "Good1000Mbps": "ami-08f15041a397e50d4",
    "Good16vCPU": "ami-0fc392bcfd8f6c725",
    "Good200Mbps": "ami-0c16fa56ab80a648b",
    "Good25Mbps": "ami-0f1c9f51edd637e8e",
    "Good5000Mbps": "ami-0ca976e8b45c852b2",
    "PerAppVeAwaf200Mbps": "ami-093df01c8613c3f9d",
    "PerAppVeAwaf25Mbps": "ami-0e8ece77555c3d4fa",
    "PerAppVeLtm200Mbps": "ami-0250156d4beb3ebad",
    "PerAppVeLtm25Mbps": "ami-0e691cb393023c502"
  },
  "ca-central-1": {
    "AdvancedWaf1000Mbps": "ami-0f5dcca6ed5452d7a",
    "AdvancedWaf16vCPU": "ami-02fb4c4bfca69e2c1",
    "AdvancedWaf200Mbps": "ami-0faac862371918f51",
    "AdvancedWaf25Mbps": "ami-06c7cb6f211c55173",
    "AdvancedWaf8vCPU": "ami-0e1d768c305e36e6b",
    "Best10000Mbps": "ami-01c9424dc0a119f60",
    "Best1000Mbps": "ami-0f04fd3860c36e7e5",
    "Best200Mbps": "ami-0763371de93f08c2a",
    "Best25Mbps": "ami-06a5504e45496d9e5",
    "Best5000Mbps": "ami-025e81795fca7d67b",
    "Better10000Mbps": "ami-020ab4baa969ee35e",
    "Better1000Mbps": "ami-060a0d7254f6e2145",
    "Better200Mbps": "ami-04a7a6cc7f9a5e268",
    "Better25Mbps": "ami-0366a80e4e3715f37",
    "Better5000Mbps": "ami-001b206940d7490f1",
    "Good10000Mbps": "ami-0a70390d0d723fc91",
    "Good1000Mbps": "ami-03d6d9cceb2da6089",
    "Good16vCPU": "ami-0561f5437cbd9c1a3",
    "Good200Mbps": "ami-0105c62f5bf81553a",
    "Good25Mbps": "ami-07bd2d749dda2dac0",
    "Good5000Mbps": "ami-09c03719f3730555e",
    "PerAppVeAwaf200Mbps": "ami-09ded5062a817bb51",
    "PerAppVeAwaf25Mbps": "ami-0ad8e21bcba3236d0",
    "PerAppVeLtm200Mbps": "ami-0379c37bdcec20bba",
    "PerAppVeLtm25Mbps": "ami-0871497dcd8a1af63"
  },
  "eu-central-1": {
    "AdvancedWaf1000Mbps": "ami-0b3ef54c7c36c8ecb",
    "AdvancedWaf16vCPU": "ami-0a4b9f26fa7269dbb",
    "AdvancedWaf200Mbps": "ami-081bdc6b4f971ebf2",
    "AdvancedWaf25Mbps": "ami-06635ee77aa78d128",
    "AdvancedWaf8vCPU": "ami-051bf5892dac796d8",
    "Best10000Mbps": "ami-05bde39038521fe8c",
    "Best1000Mbps": "ami-08213a8f5d6438958",
    "Best200Mbps": "ami-0e914b8d3fc375458",
    "Best25Mbps": "ami-04d5f1847003437fc",
    "Best5000Mbps": "ami-0ef32696b8148aa3d",
    "Better10000Mbps": "ami-073e214b1f90f465b",
    "Better1000Mbps": "ami-05281ceeece8bad24",
    "Better200Mbps": "ami-0b630890926caa000",
    "Better25Mbps": "ami-0834f02d4969d7511",
    "Better5000Mbps": "ami-0a5b868d0cb08ce44",
    "Good10000Mbps": "ami-025f0724ce607d400",
    "Good1000Mbps": "ami-0b989f2d446337b3e",
    "Good16vCPU": "ami-0cd8f45228e89b9af",
    "Good200Mbps": "ami-0a732e111a05d68e4",
    "Good25Mbps": "ami-01a2d1ddd07236b48",
    "Good5000Mbps": "ami-0c661496ff8e99302",
    "PerAppVeAwaf200Mbps": "ami-09878373cf6f4357f",
    "PerAppVeAwaf25Mbps": "ami-04c14b2baaf1c0b49",
    "PerAppVeLtm200Mbps": "ami-00ff570a93e36f9ab",
    "PerAppVeLtm25Mbps": "ami-0a1ecd4fb3f1d5125"
  },
  "eu-north-1": {
    "AdvancedWaf1000Mbps": "ami-0b2300b89fd950a21",
    "AdvancedWaf16vCPU": "ami-026447486ab126795",
    "AdvancedWaf200Mbps": "ami-06e119bfe40aec1f3",
    "AdvancedWaf25Mbps": "ami-03f92ee3525bd7d05",
    "AdvancedWaf8vCPU": "ami-097f0ef9818cb0267",
    "Best10000Mbps": "ami-0a1d5f4c3b64b0f55",
    "Best1000Mbps": "ami-0425958f33a9e8e8d",
    "Best200Mbps": "ami-00bd616d3dbf2123f",
    "Best25Mbps": "ami-04abaeea92e201e0a",
    "Best5000Mbps": "ami-06df5cfa7bc38836f",
    "Better10000Mbps": "ami-097864cabb970def3",
    "Better1000Mbps": "ami-09aaec34015f8271e",
    "Better200Mbps": "ami-04b364e01dc76029f",
    "Better25Mbps": "ami-05936b050afcf14f7",
    "Better5000Mbps": "ami-0e65a99741642666c",
    "Good10000Mbps": "ami-0eeba80a17d144c16",
    "Good1000Mbps": "ami-012e1c58d4a215bfc",
    "Good16vCPU": "ami-07c6c3d35a40f288d",
    "Good200Mbps": "ami-063264463d5494a1f",
    "Good25Mbps": "ami-08fd54b8e44c4b167",
    "Good5000Mbps": "ami-0cc620b64c244bf61",
    "PerAppVeAwaf200Mbps": "ami-0f161544871472410",
    "PerAppVeAwaf25Mbps": "ami-07f908e0317e6e1d8",
    "PerAppVeLtm200Mbps": "ami-0758a4000ef64bcf7",
    "PerAppVeLtm25Mbps": "ami-02359e0adec39a090"
  },
  "eu-west-1": {
    "AdvancedWaf1000Mbps": "ami-0346c7a28dbf7cbe4",
    "AdvancedWaf16vCPU": "ami-0addddd3ac7eab103",
    "AdvancedWaf200Mbps": "ami-001106115cd1314a7",
    "AdvancedWaf25Mbps": "ami-04ec24be9487a303e",
    "AdvancedWaf8vCPU": "ami-028cd8bcd95c9c042",
    "Best10000Mbps": "ami-0ab7c93ed028b5f4f",
    "Best1000Mbps": "ami-04d008854402e6208",
    "Best200Mbps": "ami-0f6b7456a11da3a66",
    "Best25Mbps": "ami-00f248c18d9ededea",
    "Best5000Mbps": "ami-003dc466bd7393848",
    "Better10000Mbps": "ami-0e79469e8c24a8b8a",
    "Better1000Mbps": "ami-016ead7b881ba5050",
    "Better200Mbps": "ami-045d4c652ecc8281d",
    "Better25Mbps": "ami-00278b7d6a8741493",
    "Better5000Mbps": "ami-0a6a7d69a2b382e9a",
    "Good10000Mbps": "ami-094ee58e5bf455ed8",
    "Good1000Mbps": "ami-012e34abc69df6328",
    "Good16vCPU": "ami-0fa91f7b86d25f5d0",
    "Good200Mbps": "ami-007f9c15b09a539c5",
    "Good25Mbps": "ami-093e66c5ef5f0b343",
    "Good5000Mbps": "ami-066347217e598c859",
    "PerAppVeAwaf200Mbps": "ami-05be0727cd4afc9ef",
    "PerAppVeAwaf25Mbps": "ami-03cd8b761f62c0ae2",
    "PerAppVeLtm200Mbps": "ami-05f81e956e79c0432",
    "PerAppVeLtm25Mbps": "ami-075437e787b048740"
  },
  "eu-west-2": {
    "AdvancedWaf1000Mbps": "ami-0f40105424415b3e7",
    "AdvancedWaf16vCPU": "ami-076e6cbe983ee5981",
    "AdvancedWaf200Mbps": "ami-0ec3a2434bde3408a",
    "AdvancedWaf25Mbps": "ami-0dff79c7e447430e4",
    "AdvancedWaf8vCPU": "ami-0e34f25bf92a5401f",
    "Best10000Mbps": "ami-0238dffeb652dbdf1",
    "Best1000Mbps": "ami-018d561d950d75474",
    "Best200Mbps": "ami-0f2833b7c19bd478c",
    "Best25Mbps": "ami-0453790057e9322c7",
    "Best5000Mbps": "ami-0f19bfd4ae8c520f2",
    "Better10000Mbps": "ami-0c53f9f04045d90dc",
    "Better1000Mbps": "ami-06ca46f6a3a6ce98b",
    "Better200Mbps": "ami-0dd5c26810a2424fc",
    "Better25Mbps": "ami-0558d01b61edc2877",
    "Better5000Mbps": "ami-03c4f0967f0a8a706",
    "Good10000Mbps": "ami-0358e67fc6104053f",
    "Good1000Mbps": "ami-023c0ab92f829cc70",
    "Good16vCPU": "ami-0680ef3e84a1494c8",
    "Good200Mbps": "ami-0034e8f247b9af2c4",
    "Good25Mbps": "ami-05cc0ba4a5a2732e2",
    "Good5000Mbps": "ami-0ef8e387592d729e0",
    "PerAppVeAwaf200Mbps": "ami-098e697915e5156a4",
    "PerAppVeAwaf25Mbps": "ami-02689854f758aa684",
    "PerAppVeLtm200Mbps": "ami-0abf186dbd9f4fa7e",
    "PerAppVeLtm25Mbps": "ami-0d93910508f2aa0fe"
  },
  "eu-west-3": {
    "AdvancedWaf1000Mbps": "ami-00a199aeeeea5f13d",
    "AdvancedWaf16vCPU": "ami-002064840d9b4eaf5",
    "AdvancedWaf200Mbps": "ami-058b78aa689412349",
    "AdvancedWaf25Mbps": "ami-0481fea5f40d19acd",
    "AdvancedWaf8vCPU": "ami-00cf3962f6312fbd0",
    "Best10000Mbps": "ami-0e98779e2d9dea872",
    "Best1000Mbps": "ami-06c4bd812f96d61e1",
    "Best200Mbps": "ami-03515548b4ec5c165",
    "Best25Mbps": "ami-0c942525d853031a0",
    "Best5000Mbps": "ami-09790c6f99be9f286",
    "Better10000Mbps": "ami-05cf1957d2feeb348",
    "Better1000Mbps": "ami-00a5d97b376d3d7c8",
    "Better200Mbps": "ami-006a95a0a16a2e511",
    "Better25Mbps": "ami-046a6794e67d3260e",
    "Better5000Mbps": "ami-07ebda42727066ac2",
    "Good10000Mbps": "ami-0392d30e2dc7c4aa3",
    "Good1000Mbps": "ami-0461d11f5cbefba85",
    "Good16vCPU": "ami-0053bec516a194621",
    "Good200Mbps": "ami-03b671adc6eb01dd7",
    "Good25Mbps": "ami-01fde5607a34988af",
    "Good5000Mbps": "ami-04bce8fb276234e7c",
    "PerAppVeAwaf200Mbps": "ami-0772f8fadc093e3ea",
    "PerAppVeAwaf25Mbps": "ami-00ee13c9af903a1d1",
    "PerAppVeLtm200Mbps": "ami-0c31caf883d3d7599",
    "PerAppVeLtm25Mbps": "ami-0a02b741bc9179c1b"
  },
  "me-south-1": {
    "AdvancedWaf1000Mbps": "ami-0b16b011c4804868e",
    "AdvancedWaf16vCPU": "ami-072322d43ce88038b",
    "AdvancedWaf200Mbps": "ami-069e5a864c341eb7e",
    "AdvancedWaf25Mbps": "ami-0e783a68d51fd1ff9",
    "AdvancedWaf8vCPU": "ami-00c1e710abdd11a78",
    "Best10000Mbps": "ami-00c614402e99a216b",
    "Best1000Mbps": "ami-0fd8c2c08ed351c09",
    "Best200Mbps": "ami-0ffd96d8192baf596",
    "Best25Mbps": "ami-05b135ebdd6b3e524",
    "Best5000Mbps": "ami-0cead41a4958ceb78",
    "Better10000Mbps": "ami-043971ad66fcfd6fe",
    "Better1000Mbps": "ami-0567e0706cd65ddfc",
    "Better200Mbps": "ami-0039d2f65b46e22bc",
    "Better25Mbps": "ami-0c6593dc4f85a3e7c",
    "Better5000Mbps": "ami-08861044485e6d5a1",
    "Good10000Mbps": "ami-032cbc5929dd35125",
    "Good1000Mbps": "ami-03fcb6f40788f8c55",
    "Good16vCPU": "ami-0dfdb590856cf3d91",
    "Good200Mbps": "ami-0f3a25106cb8b72a9",
    "Good25Mbps": "ami-0869b5f1d7d7cec84",
    "Good5000Mbps": "ami-0426a868e94e3aca6",
    "PerAppVeAwaf200Mbps": "ami-0d92f0e050fcd0f47",
    "PerAppVeAwaf25Mbps": "ami-0e7ce0578ee34c1b5",
    "PerAppVeLtm200Mbps": "ami-07bafee87aa8a296f",
    "PerAppVeLtm25Mbps": "ami-097c667004abda450"
  },
  "sa-east-1": {
    "AdvancedWaf1000Mbps": "ami-000b41edcd095181a",
    "AdvancedWaf16vCPU": "ami-0623b8fe9d81e050a",
    "AdvancedWaf200Mbps": "ami-0aab61a60cd04981d",
    "AdvancedWaf25Mbps": "ami-0187a16192ea75532",
    "AdvancedWaf8vCPU": "ami-01fdb1c5c1692b69a",
    "Best10000Mbps": "ami-03a018f2792867c86",
    "Best1000Mbps": "ami-08032a88bf3b14177",
    "Best200Mbps": "ami-0896aad85b083c984",
    "Best25Mbps": "ami-0da0af643f183f828",
    "Best5000Mbps": "ami-08690a5c789ffe615",
    "Better10000Mbps": "ami-0a87946c4ce1055ee",
    "Better1000Mbps": "ami-0bf668f72e0c98f24",
    "Better200Mbps": "ami-03db5fa857e31160d",
    "Better25Mbps": "ami-02e47888d188b700a",
    "Better5000Mbps": "ami-0b08cb66df1daa33c",
    "Good10000Mbps": "ami-0037ce26fad9298a7",
    "Good1000Mbps": "ami-00d0a3a36a0c42ac4",
    "Good16vCPU": "ami-0ea8ed066eddb4089",
    "Good200Mbps": "ami-0640d42f2e5e42590",
    "Good25Mbps": "ami-0568f85dfae9218b2",
    "Good5000Mbps": "ami-0c57ad852d1dea346",
    "PerAppVeAwaf200Mbps": "ami-0c19fa18609cc9e83",
    "PerAppVeAwaf25Mbps": "ami-01cebbe0b5018e9f5",
    "PerAppVeLtm200Mbps": "ami-00cc71373dd2746ba",
    "PerAppVeLtm25Mbps": "ami-072da28c528b0cc5d"
  },
  "us-east-1": {
    "AdvancedWaf1000Mbps": "ami-00922b7f79b469360",
    "AdvancedWaf16vCPU": "ami-021abfb0af3ab4a3c",
    "AdvancedWaf200Mbps": "ami-0cf8cc6332fe83ab0",
    "AdvancedWaf25Mbps": "ami-0261ff244effcd685",
    "AdvancedWaf8vCPU": "ami-03511f30040d6bbdf",
    "Best10000Mbps": "ami-0d6bce132a0740008",
    "Best1000Mbps": "ami-0b1b863ab79118227",
    "Best200Mbps": "ami-0f3abec778ebab4ce",
    "Best25Mbps": "ami-0bd0823a59f5ebdf5",
    "Best5000Mbps": "ami-0fb46f80846122478",
    "Better10000Mbps": "ami-082e10ec82fba24d3",
    "Better1000Mbps": "ami-04365071d074b5393",
    "Better200Mbps": "ami-087ad1362a2db82c4",
    "Better25Mbps": "ami-016d8fb386da12cd6",
    "Better5000Mbps": "ami-058b99f3cd2de81d9",
    "Good10000Mbps": "ami-0e492599d6a0b51dc",
    "Good1000Mbps": "ami-0a738293eaae98332",
    "Good16vCPU": "ami-0ef8c5877619cde14",
    "Good200Mbps": "ami-07c6357d8ad725b6e",
    "Good25Mbps": "ami-084c5233fce79d4ce",
    "Good5000Mbps": "ami-003d5de57e7a13067",
    "PerAppVeAwaf200Mbps": "ami-04b329f0ad97384d5",
    "PerAppVeAwaf25Mbps": "ami-045f0f4706ab8baab",
    "PerAppVeLtm200Mbps": "ami-0191682defb472bb4",
    "PerAppVeLtm25Mbps": "ami-09ebe4a19cc7cf460"
  },
  "us-east-2": {
    "AdvancedWaf1000Mbps": "ami-0997dea42764ae4c4",
    "AdvancedWaf16vCPU": "ami-09c445efd4ac781e5",
    "AdvancedWaf200Mbps": "ami-051a88c8c08e92222",
    "AdvancedWaf25Mbps": "ami-0845e7fc405de61ac",
    "AdvancedWaf8vCPU": "ami-0b9df3062b6530885",
    "Best10000Mbps": "ami-06dbf594ff1f64e0b",
    "Best1000Mbps": "ami-01b2b54795353fe32",
    "Best200Mbps": "ami-028d20678deb598d7",
    "Best25Mbps": "ami-0586456b93edbd6f7",
    "Best5000Mbps": "ami-0b8c38367cd19f95f",
    "Better10000Mbps": "ami-07ecb80bb02a457d3",
    "Better1000Mbps": "ami-0be4c11ab44f6c18d",
    "Better200Mbps": "ami-023e054804227a895",
    "Better25Mbps": "ami-0b6647a6ed769eb22",
    "Better5000Mbps": "ami-0f55e4f0172c5ae6f",
    "Good10000Mbps": "ami-047281164f7b7eab5",
    "Good1000Mbps": "ami-0035d684b04f97a5d",
    "Good16vCPU": "ami-02b8d070f54cd6539",
    "Good200Mbps": "ami-0ce03bf35ad94641a",
    "Good25Mbps": "ami-0fb0ef3b8a9d318cf",
    "Good5000Mbps": "ami-01f535803c08cb38c",
    "PerAppVeAwaf200Mbps": "ami-05cef1e70114df277",
    "PerAppVeAwaf25Mbps": "ami-0c62ab590fba916ae",
    "PerAppVeLtm200Mbps": "ami-0942771f4a614a53e",
    "PerAppVeLtm25Mbps": "ami-063e1f506cf40071a"
  },
  "us-gov-east-1": {
    "AdvancedWaf1000Mbps": "ami-0d424ed1a9dd5c4af",
    "AdvancedWaf16vCPU": "ami-0ec49a93b9e45c085",
    "AdvancedWaf200Mbps": "ami-02a5a2e21608845d0",
    "AdvancedWaf25Mbps": "ami-0c66323d632cff949",
    "AdvancedWaf8vCPU": "ami-0416b579bea80774c",
    "Best10000Mbps": "ami-0ab09bf388bb61aea",
    "Best1000Mbps": "ami-0e12f3aeb5d16ba2c",
    "Best200Mbps": "ami-0e57c9f006dbbbbe7",
    "Best25Mbps": "ami-09f7e09cf2cac2715",
    "Best5000Mbps": "ami-0fd6fad9e41ce8e30",
    "Better10000Mbps": "ami-05918b483c4b7ddc7",
    "Better1000Mbps": "ami-012eab746878804f3",
    "Better200Mbps": "ami-0a5ab6feab2d01e03",
    "Better25Mbps": "ami-0d436ba955aeb3fe9",
    "Better5000Mbps": "ami-02868a49200d55218",
    "Good10000Mbps": "ami-050f66b898fb48a07",
    "Good1000Mbps": "ami-068cc541f1589ebd8",
    "Good16vCPU": "ami-00a8d4679901e6283",
    "Good200Mbps": "ami-04d4c40197f2db753",
    "Good25Mbps": "ami-0f026a974d2a43524",
    "Good5000Mbps": "ami-00efe52bd3f0b5dae",
    "PerAppVeAwaf200Mbps": "ami-0b949048a1aaa018f",
    "PerAppVeAwaf25Mbps": "ami-037e2366774fdfd27",
    "PerAppVeLtm200Mbps": "ami-0bdedc75d25be2a33",
    "PerAppVeLtm25Mbps": "ami-01da3768057549790"
  },
  "us-gov-west-1": {
    "AdvancedWaf1000Mbps": "ami-07b74a8427ade0d37",
    "AdvancedWaf16vCPU": "ami-0cb5fe690499aa3d1",
    "AdvancedWaf200Mbps": "ami-02c719bb9e8cb776c",
    "AdvancedWaf25Mbps": "ami-089a1ee88f43c083b",
    "AdvancedWaf8vCPU": "ami-05843ebdadd2dd375",
    "Best10000Mbps": "ami-0e3cb128b322bc57f",
    "Best1000Mbps": "ami-010114add722a56ba",
    "Best200Mbps": "ami-03f54328bcdc19bd7",
    "Best25Mbps": "ami-0dc3da9e8de908f71",
    "Best5000Mbps": "ami-0e354e3cb67b46f5d",
    "Better10000Mbps": "ami-008a75c4babc8af59",
    "Better1000Mbps": "ami-008515e5f92f6c328",
    "Better200Mbps": "ami-0251f36d03de677d1",
    "Better25Mbps": "ami-05627a6291053efe1",
    "Better5000Mbps": "ami-03ce04458864d5796",
    "Good10000Mbps": "ami-09edb68877d61968b",
    "Good1000Mbps": "ami-024702ad6fb202cfa",
    "Good16vCPU": "ami-00d2fbe4efb9c27c2",
    "Good200Mbps": "ami-009af7af8e0e4c5c7",
    "Good25Mbps": "ami-06f171c565829fc1f",
    "Good5000Mbps": "ami-0158d72f980a61d8e",
    "PerAppVeAwaf200Mbps": "ami-02aac947bfd5e66ca",
    "PerAppVeAwaf25Mbps": "ami-08e3a6efdf99df42a",
    "PerAppVeLtm200Mbps": "ami-049412c440b535fc3",
    "PerAppVeLtm25Mbps": "ami-0d8229edbdf8565a4"
  },
  "us-west-1": {
    "AdvancedWaf1000Mbps": "ami-013a004b654011798",
    "AdvancedWaf16vCPU": "ami-024ca215c18297c90",
    "AdvancedWaf200Mbps": "ami-088ab573a5ae5f526",
    "AdvancedWaf25Mbps": "ami-094d010ab35943550",
    "AdvancedWaf8vCPU": "ami-0ba0e41ff7a083a1d",
    "Best10000Mbps": "ami-0b0aeae194fe84693",
    "Best1000Mbps": "ami-02d78b0d643792e33",
    "Best200Mbps": "ami-0b3e19d9ac01acd82",
    "Best25Mbps": "ami-05ca7b074dddffcc5",
    "Best5000Mbps": "ami-0fa52b3bdd8b3187e",
    "Better10000Mbps": "ami-0105c1879466255a4",
    "Better1000Mbps": "ami-064b5fbb3ff71d94e",
    "Better200Mbps": "ami-0c1d4725c77caf602",
    "Better25Mbps": "ami-0d461928533a01f3a",
    "Better5000Mbps": "ami-0194103c481bdb757",
    "Good10000Mbps": "ami-03389dc2c39ddbece",
    "Good1000Mbps": "ami-0425dbd42a3fa1b0d",
    "Good16vCPU": "ami-01c443ddd006a9923",
    "Good200Mbps": "ami-0e615b426cb88fe24",
    "Good25Mbps": "ami-0bf064a7ca932e373",
    "Good5000Mbps": "ami-07a90c292bcb344e5",
    "PerAppVeAwaf200Mbps": "ami-01613cd067ff92460",
    "PerAppVeAwaf25Mbps": "ami-08208da7a634a5374",
    "PerAppVeLtm200Mbps": "ami-0fb8d3ab2161a2013",
    "PerAppVeLtm25Mbps": "ami-0e8c49552bf5249d5"
  },
  "us-west-2": {
    "AdvancedWaf1000Mbps": "ami-03bd4d0c1d5115d2c",
    "AdvancedWaf16vCPU": "ami-01fde504ecb2d4312",
    "AdvancedWaf200Mbps": "ami-01eb7a5cec1fe98f9",
    "AdvancedWaf25Mbps": "ami-06ed67f3cadfe1a6a",
    "AdvancedWaf8vCPU": "ami-05ecc342e561100a8",
    "Best10000Mbps": "ami-06254b7d72c86d6de",
    "Best1000Mbps": "ami-0d5f48eb33fa32123",
    "Best200Mbps": "ami-055f80642de6e2b86",
    "Best25Mbps": "ami-0308940b1fdb87ecf",
    "Best5000Mbps": "ami-00f9e3e31a487bfd3",
    "Better10000Mbps": "ami-0849546751704ce7e",
    "Better1000Mbps": "ami-0a2bb3692d84beba5",
    "Better200Mbps": "ami-05151a063701b0902",
    "Better25Mbps": "ami-012502ddc9620600c",
    "Better5000Mbps": "ami-06452bf509b948e31",
    "Good10000Mbps": "ami-01d37e965fa18873a",
    "Good1000Mbps": "ami-037002e2e592ebc1c",
    "Good16vCPU": "ami-09b0b93599aa615df",
    "Good200Mbps": "ami-05cad7b4ffa86c68a",
    "Good25Mbps": "ami-0deabcb577dc6412c",
    "Good5000Mbps": "ami-08e71cea1e0567df7",
    "PerAppVeAwaf200Mbps": "ami-021c0f0f2d5830e66",
    "PerAppVeAwaf25Mbps": "ami-0250af638732cec83",
    "PerAppVeLtm200Mbps": "ami-053255624eb2d7224",
    "PerAppVeLtm25Mbps": "ami-02eb08afd79cd5a39"
  }
}